[
  {"timestamp": "2024-02-28T13:15:00Z", "level": "INFO", "service": "infrastructure", "host": "deploy-bot", "message": "Applying ConfigMap update to kube-system/coredns. Change: added custom DNS stub zone for internal.company.com. PR #8821", "trace_id": null},
  {"timestamp": "2024-02-28T13:15:44Z", "level": "INFO", "service": "infrastructure", "host": "kube-controller", "message": "ConfigMap kube-system/coredns updated. CoreDNS pods will reload config automatically.", "trace_id": null},
  {"timestamp": "2024-02-28T13:16:01Z", "level": "ERROR", "service": "infrastructure", "host": "coredns-7f9d8-abc", "message": "Config reload failed: syntax error in Corefile line 14: unexpected token 'stubzone'. Plugin 'stubzone' not found.", "trace_id": null},
  {"timestamp": "2024-02-28T13:16:01Z", "level": "ERROR", "service": "infrastructure", "host": "coredns-7f9d8-def", "message": "Config reload failed: syntax error in Corefile line 14: unexpected token 'stubzone'. Plugin 'stubzone' not found.", "trace_id": null},
  {"timestamp": "2024-02-28T13:16:02Z", "level": "CRITICAL", "service": "infrastructure", "host": "coredns-7f9d8-abc", "message": "CrashLoopBackOff: pod exiting with code 1. Kubernetes will restart.", "trace_id": null},
  {"timestamp": "2024-02-28T13:16:02Z", "level": "CRITICAL", "service": "infrastructure", "host": "coredns-7f9d8-def", "message": "CrashLoopBackOff: pod exiting with code 1. Kubernetes will restart.", "trace_id": null},
  {"timestamp": "2024-02-28T13:16:45Z", "level": "ERROR", "service": "user-service", "host": "user-pod-5a2c-qrs", "message": "DNS resolution failed: dial tcp: lookup payment-service.default.svc.cluster.local: no such host", "trace_id": "dns-001"},
  {"timestamp": "2024-02-28T13:16:46Z", "level": "ERROR", "service": "order-service", "host": "order-pod-8b1d-tuv", "message": "DNS resolution failed: dial tcp: lookup inventory-service.default.svc.cluster.local: no such host", "trace_id": "dns-002"},
  {"timestamp": "2024-02-28T13:16:50Z", "level": "ERROR", "service": "recommendation-service", "host": "rec-pod-3e7f-wxy", "message": "DNS resolution failed: dial tcp: lookup catalog-service.default.svc.cluster.local: no such host", "trace_id": "dns-003"},
  {"timestamp": "2024-02-28T13:17:00Z", "level": "WARN", "service": "api-gateway", "host": "gw-pod-2x9f-a1b2", "message": "Upstream circuit breaker OPEN for user-service (DNS failures). Failing fast for affected routes.", "trace_id": null},
  {"timestamp": "2024-02-28T13:17:05Z", "level": "WARN", "service": "api-gateway", "host": "gw-pod-2x9f-a1b2", "message": "Upstream circuit breaker OPEN for order-service (DNS failures). Failing fast for affected routes.", "trace_id": null},
  {"timestamp": "2024-02-28T13:17:10Z", "level": "CRITICAL", "service": "monitoring", "host": "prometheus-0", "message": "ALERT FIRING: CoreDNSCrashLoopDetected + ServiceMeshDNSFailures. Error rate 54.3% across cluster. Severity=P2", "trace_id": null},
  {"timestamp": "2024-02-28T13:18:00Z", "level": "INFO", "service": "infrastructure", "host": "coredns-7f9d8-abc", "message": "Restart attempt 2/5. Still failing with same config error.", "trace_id": null},
  {"timestamp": "2024-02-28T13:30:00Z", "level": "INFO", "service": "infrastructure", "host": "deploy-bot", "message": "On-call SRE engaged. Investigating CoreDNS crash loop. Last change: ConfigMap update at 13:15:44Z", "trace_id": null},
  {"timestamp": "2024-02-28T13:35:00Z", "level": "INFO", "service": "infrastructure", "host": "coredns-7f9d8-abc", "message": "Restart attempt 8/5 (backoff). Pod in CrashLoopBackOff with 5min backoff. DNS resolution intermittent - some cached entries still resolving.", "trace_id": null},
  {"timestamp": "2024-02-28T13:40:00Z", "level": "WARN", "service": "infrastructure", "host": "kube-controller", "message": "WARNING: CoreDNS pods have been in CrashLoopBackOff for 24 minutes. Cluster DNS degraded. Services using IP-based routing unaffected.", "trace_id": null}
]
